benchmarks/benchmark_batched_envs.py
benchmarks/conftest.py
benchmarks/requirements.txt
benchmarks/test_collectors_benchmark.py
benchmarks/test_compressed_storage_benchmark.py
benchmarks/test_envs_benchmark.py
benchmarks/test_llm.py
benchmarks/test_objectives_benchmarks.py
benchmarks/test_replaybuffer_benchmark.py
benchmarks/ecosystem/gym_env_throughput.py
benchmarks/ecosystem/vmas_rllib_vs_torchrl_sampling_performance.py
benchmarks/storage/benchmark_sample_latency_over_rpc.py
sota-check/README.md
sota-implementations/README.md
sota-implementations/a2c/README.md
sota-implementations/a2c/a2c_atari.py
sota-implementations/a2c/a2c_mujoco.py
sota-implementations/a2c/utils_atari.py
sota-implementations/a2c/utils_mujoco.py
sota-implementations/bandits/README.md
sota-implementations/bandits/dqn.py
sota-implementations/cql/cql_offline.py
sota-implementations/cql/cql_online.py
sota-implementations/cql/discrete_cql_offline.py
sota-implementations/cql/discrete_cql_online.py
sota-implementations/cql/utils.py
sota-implementations/crossq/crossq.py
sota-implementations/crossq/utils.py
sota-implementations/ddpg/ddpg.py
sota-implementations/ddpg/utils.py
sota-implementations/decision_transformer/dt.py
sota-implementations/decision_transformer/lamb.py
sota-implementations/decision_transformer/online_dt.py
sota-implementations/decision_transformer/utils.py
sota-implementations/discrete_sac/discrete_sac.py
sota-implementations/discrete_sac/utils.py
sota-implementations/dqn/README.md
sota-implementations/dqn/dqn_atari.py
sota-implementations/dqn/dqn_cartpole.py
sota-implementations/dqn/utils_atari.py
sota-implementations/dqn/utils_cartpole.py
sota-implementations/dreamer/README.md
sota-implementations/dreamer/dreamer.py
sota-implementations/dreamer/dreamer_utils.py
sota-implementations/expert-iteration/README.md
sota-implementations/expert-iteration/ei_utils.py
sota-implementations/expert-iteration/expert-iteration-async.py
sota-implementations/expert-iteration/expert-iteration-sync.py
torchrl_nightly-2025.9.1.dist-info/LICENSE
torchrl_nightly-2025.9.1.dist-info/METADATA
torchrl_nightly-2025.9.1.dist-info/WHEEL
torchrl_nightly-2025.9.1.dist-info/top_level.txt
torchrl_nightly-2025.9.1.dist-info/RECORD
