Metadata-Version: 2.4
Name: torchrl-nightly
Version: 2025.9.1
Summary: A modular, primitive-first, python-first PyTorch library for Reinforcement Learning
Author-email: torchrl contributors <vmoens@fb.com>
Maintainer-email: torchrl contributors <vmoens@fb.com>
Project-URL: Homepage, https://github.com/pytorch/rl
Project-URL: Documentation, https://pytorch.org/rl
Project-URL: Repository, https://github.com/pytorch/rl
Project-URL: Bug Tracker, https://github.com/pytorch/rl/issues
Project-URL: twitter, https://x.com/torchrl1
Project-URL: linkedin, https://www.linkedin.com/company/torchrl
Project-URL: discord, https://discord.gg/cZs26Qq3Dd
Project-URL: benchmark, https://docs.pytorch.org/rl/dev/bench/
Keywords: reinforcement-learning,pytorch,rl,machine-learning
Classifier: Programming Language :: Python :: 3.9
Classifier: Programming Language :: Python :: 3.10
Classifier: Programming Language :: Python :: 3.11
Classifier: Programming Language :: Python :: 3.12
Classifier: Programming Language :: Python :: 3.13
Classifier: Operating System :: OS Independent
Classifier: Development Status :: 4 - Beta
Classifier: Intended Audience :: Developers
Classifier: Intended Audience :: Science/Research
Classifier: Topic :: Scientific/Engineering :: Artificial Intelligence
Requires-Python: >=3.9
License-File: LICENSE
Requires-Dist: torch>=2.1.0
Requires-Dist: numpy
Requires-Dist: packaging
Requires-Dist: cloudpickle
Requires-Dist: tensordict-nightly
Provides-Extra: atari
Requires-Dist: gymnasium[atari]; extra == "atari"
Provides-Extra: dm-control
Requires-Dist: dm_control; extra == "dm-control"
Provides-Extra: replay-buffer
Requires-Dist: torch>=2.7.0; extra == "replay-buffer"
Provides-Extra: gym-continuous
Requires-Dist: gymnasium<1.0; extra == "gym-continuous"
Requires-Dist: mujoco; extra == "gym-continuous"
Provides-Extra: rendering
Requires-Dist: moviepy<2.0.0; extra == "rendering"
Provides-Extra: tests
Requires-Dist: pytest; extra == "tests"
Requires-Dist: pyyaml; extra == "tests"
Requires-Dist: pytest-instafail; extra == "tests"
Requires-Dist: scipy; extra == "tests"
Requires-Dist: pytest-mock; extra == "tests"
Requires-Dist: pytest-cov; extra == "tests"
Requires-Dist: pytest-asyncio; extra == "tests"
Requires-Dist: pytest-benchmark; extra == "tests"
Requires-Dist: pytest-rerunfailures; extra == "tests"
Requires-Dist: pytest-error-for-skips; extra == "tests"
Provides-Extra: utils
Requires-Dist: tensorboard; extra == "utils"
Requires-Dist: wandb; extra == "utils"
Requires-Dist: tqdm; extra == "utils"
Requires-Dist: hydra-core>=1.1; extra == "utils"
Requires-Dist: hydra-submitit-launcher; extra == "utils"
Provides-Extra: checkpointing
Requires-Dist: torchsnapshot; extra == "checkpointing"
Provides-Extra: offline-data
Requires-Dist: huggingface_hub; extra == "offline-data"
Requires-Dist: minari; extra == "offline-data"
Requires-Dist: requests; extra == "offline-data"
Requires-Dist: tqdm; extra == "offline-data"
Requires-Dist: torchvision; extra == "offline-data"
Requires-Dist: scikit-learn; extra == "offline-data"
Requires-Dist: pandas; extra == "offline-data"
Requires-Dist: h5py; extra == "offline-data"
Requires-Dist: pillow; extra == "offline-data"
Provides-Extra: marl
Requires-Dist: vmas>=1.2.10; extra == "marl"
Requires-Dist: pettingzoo>=1.24.1; extra == "marl"
Requires-Dist: dm-meltingpot; extra == "marl"
Provides-Extra: open-spiel
Requires-Dist: open_spiel>=1.5; extra == "open-spiel"
Provides-Extra: brax
Requires-Dist: jax[cuda12]>=0.7.0; extra == "brax"
Requires-Dist: brax; extra == "brax"
Provides-Extra: llm
Requires-Dist: transformers; extra == "llm"
Requires-Dist: vllm; extra == "llm"
Requires-Dist: playwright; extra == "llm"
Requires-Dist: datasets; extra == "llm"
Requires-Dist: langdetect; extra == "llm"
Requires-Dist: nltk; extra == "llm"
Requires-Dist: immutabledict; extra == "llm"
Requires-Dist: accelerate; extra == "llm"
Requires-Dist: sentencepiece; extra == "llm"
Requires-Dist: protobuf; extra == "llm"
Requires-Dist: einops; extra == "llm"
Requires-Dist: safetensors; extra == "llm"
Provides-Extra: dev
Requires-Dist: pre-commit; extra == "dev"
Requires-Dist: autoflake; extra == "dev"
Dynamic: license-file
